proteotools/__init__.py
proteotools/convert.py
proteotools/proteowizard.py
proteotools/search.py
proteotools/software.py
proteotools/tpp.py
proteotools-0.2.1.dist-info/METADATA
proteotools-0.2.1.dist-info/WHEEL
proteotools-0.2.1.dist-info/top_level.txt
proteotools-0.2.1.dist-info/RECORD
